coconut_pytorch/__init__.py
coconut_pytorch/coconut.py
coconut_pytorch/multi_stream_coconut.py
coconut_pytorch-0.0.32.dist-info/METADATA
coconut_pytorch-0.0.32.dist-info/WHEEL
coconut_pytorch-0.0.32.dist-info/licenses/LICENSE
coconut_pytorch-0.0.32.dist-info/RECORD
