Metadata-Version: 2.4
Name: coconut-pytorch
Version: 0.0.32
Summary: Coconut in Pytorch
Project-URL: Homepage, https://pypi.org/project/coconut-pytorch/
Project-URL: Repository, https://github.com/lucidrains/coconut-pytorch
Author-email: Phil Wang <lucidrains@gmail.com>
License: MIT License
License-File: LICENSE
Keywords: artificial intelligence,attention mechanism,continuous latent tokens,deep learning,reasoning,transformers
Classifier: Development Status :: 4 - Beta
Classifier: Intended Audience :: Developers
Classifier: License :: OSI Approved :: MIT License
Classifier: Programming Language :: Python :: 3.8
Classifier: Topic :: Scientific/Engineering :: Artificial Intelligence
Requires-Python: >=3.9
Requires-Dist: einops>=0.8.0
Requires-Dist: hyper-connections>=0.1.0
Requires-Dist: rotary-embedding-torch>=0.5.3
Requires-Dist: torch>=2.4
Requires-Dist: x-transformers>=1.42.26
